{ "_id" : { "$oid" : "5bb9b9d9f5e0a646939a3fe4" }, "tweet_text" : "El Gobierno planea un impuesto del 0,2% a la compra de acciones https:// elpais.com/economia/2018/ 10/05/actualidad/1538768392_773536.html?id_externo_rsoc=TW_CC &nbsp; … vía @ elpais_economia", "snapshot_timestamp" : "Sun Oct 07 07:46:32 +0000 2018", "snapshot_id" : 36, "retweet_count" : "", "id_tweet" : "1048839828887015424", "publisher_screen_name" : "antonio_maqueda", "bot_screen_name" : "tiagosi65456343", "impression_order" : 0, "tweet_created_at" : "12:37 AM - 7 Oct 2018", "publisher_id" : "267311504", "tweet_amount_of_likes" : "", "tweet_amount_of_comments" : "" }
{ "_id" : { "$oid" : "5bb9b9d9f5e0a646939a3fe5" }, "tweet_text" : "“Yo no me consideraba un drogadicto. Creía que esos eran los que se clavaban agujas en el brazo, pero en realidad yo era el mayor yonqui. Estuve muy cerca de morir” http:// ow.ly/8dYN30m893H &nbsp;", "snapshot_timestamp" : "Sun Oct 07 07:46:32 +0000 2018", "snapshot_id" : 36, "retweet_count" : "", "id_tweet" : "1048841054991134720", "publisher_screen_name" : "el_pais", "bot_screen_name" : "tiagosi65456343", "impression_order" : 1, "tweet_created_at" : "12:42 AM - 7 Oct 2018", "publisher_id" : "7996082", "tweet_amount_of_likes" : "", "tweet_amount_of_comments" : "" }
{ "_id" : { "$oid" : "5bb9b9d9f5e0a646939a3fe6" }, "tweet_text" : "# MaisLidas Jovem que trabalhava em alto-mar fica à deriva por 49 dias e sobrevive fazendo fogueiras com madeira retirada da própria embarcação https:// bbc.in/2O2csBj &nbsp; pic.twitter.com/ONAZHM46ck", "snapshot_timestamp" : "Sun Oct 07 07:46:32 +0000 2018", "snapshot_id" : 36, "retweet_count" : "", "id_tweet" : "1048838103945891840", "publisher_screen_name" : "bbcbrasil", "bot_screen_name" : "tiagosi65456343", "impression_order" : 2, "tweet_created_at" : "12:31 AM - 7 Oct 2018", "publisher_id" : "790680", "tweet_amount_of_likes" : "", "tweet_amount_of_comments" : "" }
{ "_id" : { "$oid" : "5bb9b9d9f5e0a646939a3fe7" }, "tweet_text" : "La gran farsa del padre de Nadia. El fiscal vio tan claro el caso que inclusó sopesó aumentar la pena de los progenitores de la niña http:// ow.ly/ggQP30m88TI &nbsp;", "snapshot_timestamp" : "Sun Oct 07 07:46:32 +0000 2018", "snapshot_id" : 36, "retweet_count" : "", "id_tweet" : "1048838014368206848", "publisher_screen_name" : "el_pais", "bot_screen_name" : "tiagosi65456343", "impression_order" : 3, "tweet_created_at" : "12:30 AM - 7 Oct 2018", "publisher_id" : "7996082", "tweet_amount_of_likes" : "", "tweet_amount_of_comments" : "" }
{ "_id" : { "$oid" : "5bb9b9d9f5e0a646939a3fe8" }, "tweet_text" : "a gran farsa del padre de Nadia. El fiscal vio tan claro el caso que inclusó sopesó aumentar la pena de los progenitores de la niña http:// ow.ly/ggQP30m88TI &nbsp;", "snapshot_timestamp" : "Sun Oct 07 07:46:32 +0000 2018", "snapshot_id" : 36, "retweet_count" : "", "id_tweet" : "1048837797727989761", "publisher_screen_name" : "el_pais", "bot_screen_name" : "tiagosi65456343", "impression_order" : 4, "tweet_created_at" : "12:29 AM - 7 Oct 2018", "publisher_id" : "7996082", "tweet_amount_of_likes" : "", "tweet_amount_of_comments" : "" }
{ "_id" : { "$oid" : "5bb9b9d9f5e0a646939a3fe9" }, "tweet_text" : "Hamilton vence GP do Japão e abre 67 pontos de vantagem sobre Vettel https:// www1.folha.uol.com.br/esporte/2018/1 0/hamilton-vence-gp-do-japao-e-abre-67-pontos-de-vantagem-sobre-vettel.shtml?utm_source=twitter&amp;utm_medium=social&amp;utm_campaign=twfolha &nbsp; …", "snapshot_timestamp" : "Sun Oct 07 07:46:32 +0000 2018", "snapshot_id" : 36, "retweet_count" : "", "id_tweet" : "1048836833419960320", "publisher_screen_name" : "folha", "bot_screen_name" : "tiagosi65456343", "impression_order" : 5, "tweet_created_at" : "12:26 AM - 7 Oct 2018", "publisher_id" : "14594813", "tweet_amount_of_likes" : "", "tweet_amount_of_comments" : "" }
{ "_id" : { "$oid" : "5bb9b9daf5e0a646939a3fea" }, "tweet_text" : "Senado americano confirma indicação de Kavanaugh por Trump para a Suprema Corte https:// bbc.in/2PiZI5Y &nbsp; pic.twitter.com/vFYdknjdHv", "snapshot_timestamp" : "Sun Oct 07 07:46:32 +0000 2018", "snapshot_id" : 36, "retweet_count" : "", "id_tweet" : "1048834869021872129", "publisher_screen_name" : "bbcbrasil", "bot_screen_name" : "tiagosi65456343", "impression_order" : 6, "tweet_created_at" : "12:18 AM - 7 Oct 2018", "publisher_id" : "790680", "tweet_amount_of_likes" : "", "tweet_amount_of_comments" : "" }
{ "_id" : { "$oid" : "5bb9b9daf5e0a646939a3feb" }, "tweet_text" : "Alquilar se pone imposible (y no solo por el precio) http:// ow.ly/UWWH30m88Ly &nbsp;", "snapshot_timestamp" : "Sun Oct 07 07:46:32 +0000 2018", "snapshot_id" : 36, "retweet_count" : "", "id_tweet" : "1048834120913227776", "publisher_screen_name" : "el_pais", "bot_screen_name" : "tiagosi65456343", "impression_order" : 7, "tweet_created_at" : "12:15 AM - 7 Oct 2018", "publisher_id" : "7996082", "tweet_amount_of_likes" : "", "tweet_amount_of_comments" : "" }
{ "_id" : { "$oid" : "5bb9b9daf5e0a646939a3fec" }, "tweet_text" : "Novo entrave atrasa plano de trem para ligar região de Campinas a São Paulo https:// www1.folha.uol.com.br/cotidiano/2018 /10/novo-entrave-atrasa-plano-de-trem-para-ligar-regiao-de-campinas-a-sao-paulo.shtml?utm_source=twitter&amp;utm_medium=social&amp;utm_campaign=twfolha &nbsp; …", "snapshot_timestamp" : "Sun Oct 07 07:46:32 +0000 2018", "snapshot_id" : 36, "retweet_count" : "", "id_tweet" : "1048830544698658817", "publisher_screen_name" : "folha", "bot_screen_name" : "tiagosi65456343", "impression_order" : 8, "tweet_created_at" : "12:01 AM - 7 Oct 2018", "publisher_id" : "14594813", "tweet_amount_of_likes" : "", "tweet_amount_of_comments" : "" }
{ "_id" : { "$oid" : "5bb9b9daf5e0a646939a3fed" }, "tweet_text" : "Idosos de Curitiba usam a dança para desafiar as limitações da idade. O @ reporterbrasil mostrou a empolgação do pessoal! Clique pra ver! pic.twitter.com/CJTfLtAw3o", "snapshot_timestamp" : "Sun Oct 07 07:46:32 +0000 2018", "snapshot_id" : 36, "retweet_count" : "", "id_tweet" : "1048830283636723712", "publisher_screen_name" : "ebcnarede", "bot_screen_name" : "tiagosi65456343", "impression_order" : 9, "tweet_created_at" : "12:00 AM - 7 Oct 2018", "publisher_id" : "421268817", "tweet_amount_of_likes" : "", "tweet_amount_of_comments" : "" }
{ "_id" : { "$oid" : "5bb9b9daf5e0a646939a3fee" }, "tweet_text" : "&gt; @ esportefera Ex-jogador de basquete Paul Pierce acredita que a Terra é plana e explica o motivo http:// bit.ly/2yktgIV &nbsp; pic.twitter.com/XJoihzx92s", "snapshot_timestamp" : "Sun Oct 07 07:46:32 +0000 2018", "snapshot_id" : 36, "retweet_count" : "", "id_tweet" : "1048830283527741441", "publisher_screen_name" : "Estadao", "bot_screen_name" : "tiagosi65456343", "impression_order" : 10, "tweet_created_at" : "12:00 AM - 7 Oct 2018", "publisher_id" : "9317502", "tweet_amount_of_likes" : "", "tweet_amount_of_comments" : "" }
{ "_id" : { "$oid" : "5bb9b9daf5e0a646939a3fef" }, "tweet_text" : "Flamengo confirma lesão na coxa de Diego: https:// glo.bo/2pC6AQm &nbsp; pic.twitter.com/QMfls0cKrl", "snapshot_timestamp" : "Sun Oct 07 07:46:32 +0000 2018", "snapshot_id" : 36, "retweet_count" : "", "id_tweet" : "1048830282953121798", "publisher_screen_name" : "JornalOGlobo", "bot_screen_name" : "tiagosi65456343", "impression_order" : 11, "tweet_created_at" : "12:00 AM - 7 Oct 2018", "publisher_id" : "54341363", "tweet_amount_of_likes" : "", "tweet_amount_of_comments" : "" }
{ "_id" : { "$oid" : "5bb9c7eff5e0a646939a4002" }, "tweet_text" : "La batalla de Casado y Rivera por liderar la oposición y encarnar la mano dura en Cataluña provoca una escalada de incongruencias y rectificaciones http:// ow.ly/y03x30m89DR &nbsp;", "snapshot_timestamp" : "Sun Oct 07 08:46:39 +0000 2018", "snapshot_id" : 37, "retweet_count" : "", "id_tweet" : "1048856159757721601", "publisher_screen_name" : "el_pais", "bot_screen_name" : "tiagosi65456343", "impression_order" : 0, "tweet_created_at" : "1:42 AM - 7 Oct 2018", "publisher_id" : "7996082", "tweet_amount_of_likes" : "", "tweet_amount_of_comments" : "" }
{ "_id" : { "$oid" : "5bb9c7eff5e0a646939a4003" }, "tweet_text" : "Exposição a germes na infância aumenta chances de proteger organismo contra alergias, aponta pesquisa # saúde # alergia # pediatria https:// bbc.in/2yajbhG &nbsp; pic.twitter.com/HqUDCxoVEa", "snapshot_timestamp" : "Sun Oct 07 08:46:39 +0000 2018", "snapshot_id" : 37, "retweet_count" : "", "id_tweet" : "1048853449729875968", "publisher_screen_name" : "bbcbrasil", "bot_screen_name" : "tiagosi65456343", "impression_order" : 1, "tweet_created_at" : "1:32 AM - 7 Oct 2018", "publisher_id" : "790680", "tweet_amount_of_likes" : "", "tweet_amount_of_comments" : "" }
{ "_id" : { "$oid" : "5bb9c7eff5e0a646939a4004" }, "tweet_text" : "Concurso da ONG SOS Mata Atlântica tem votação das melhores imagens do bioma https:// www1.folha.uol.com.br/ciencia/2018/1 0/concurso-da-ong-sos-mata-atlantica-tem-votacao-das-melhores-imagens-do-bioma.shtml?utm_source=twitter&amp;utm_medium=social&amp;utm_campaign=twfolha &nbsp; …", "snapshot_timestamp" : "Sun Oct 07 08:46:39 +0000 2018", "snapshot_id" : 37, "retweet_count" : "", "id_tweet" : "1048853195647328256", "publisher_screen_name" : "folha", "bot_screen_name" : "tiagosi65456343", "impression_order" : 2, "tweet_created_at" : "1:31 AM - 7 Oct 2018", "publisher_id" : "14594813", "tweet_amount_of_likes" : "", "tweet_amount_of_comments" : "" }
{ "_id" : { "$oid" : "5bb9c7f0f5e0a646939a4005" }, "tweet_text" : "# EleccionesBrasil \"Prefiero que mi hijo muera en un accidente a que ande con un bigotón por ahí\". Estas son algunas de las frases más polémicas del ultraderechista Jair Bolsonaro, candidato presidencial brasileño http:// ow.ly/8XKU30m83Ow &nbsp; pic.twitter.com/B1hGhHBluZ", "snapshot_timestamp" : "Sun Oct 07 08:46:39 +0000 2018", "snapshot_id" : 37, "retweet_count" : "", "id_tweet" : "1048852953531072512", "publisher_screen_name" : "el_pais", "bot_screen_name" : "tiagosi65456343", "impression_order" : 3, "tweet_created_at" : "1:30 AM - 7 Oct 2018", "publisher_id" : "7996082", "tweet_amount_of_likes" : "", "tweet_amount_of_comments" : "" }
{ "_id" : { "$oid" : "5bb9c7f0f5e0a646939a4006" }, "tweet_text" : "Obra de arte de Banksy se autodestrói após ser vendida por mais de 1 milhão de libras https:// bbc.in/2y5vlcx &nbsp; pic.twitter.com/yiewYnwZ6p", "snapshot_timestamp" : "Sun Oct 07 08:46:39 +0000 2018", "snapshot_id" : 37, "retweet_count" : "", "id_tweet" : "1048852652124250112", "publisher_screen_name" : "bbcbrasil", "bot_screen_name" : "tiagosi65456343", "impression_order" : 4, "tweet_created_at" : "1:28 AM - 7 Oct 2018", "publisher_id" : "790680", "tweet_amount_of_likes" : "", "tweet_amount_of_comments" : "" }
{ "_id" : { "$oid" : "5bb9c7f0f5e0a646939a4007" }, "tweet_text" : "Favorito no PR, Ratinho Junior se vende como representante do 'novo' https:// www1.folha.uol.com.br/poder/2018/10/ favorito-no-pr-ratinho-junior-se-vende-como-representante-do-novo.shtml?utm_source=twitter&amp;utm_medium=social&amp;utm_campaign=twfolha &nbsp; …", "snapshot_timestamp" : "Sun Oct 07 08:46:39 +0000 2018", "snapshot_id" : 37, "retweet_count" : "", "id_tweet" : "1048850929762619392", "publisher_screen_name" : "folha", "bot_screen_name" : "tiagosi65456343", "impression_order" : 5, "tweet_created_at" : "1:22 AM - 7 Oct 2018", "publisher_id" : "14594813", "tweet_amount_of_likes" : "", "tweet_amount_of_comments" : "" }
{ "_id" : { "$oid" : "5bb9c7f0f5e0a646939a4008" }, "tweet_text" : "Los que devolvieron el gasto de las ‘black’ se libran de prisión aunque derrocharan https:// elpais.com/economia/2018/ 10/04/actualidad/1538681752_014547.html &nbsp; …", "snapshot_timestamp" : "Sun Oct 07 08:46:39 +0000 2018", "snapshot_id" : 37, "retweet_count" : "", "id_tweet" : "1048849402838831104", "publisher_screen_name" : "idebarron", "bot_screen_name" : "tiagosi65456343", "impression_order" : 6, "tweet_created_at" : "1:15 AM - 7 Oct 2018", "publisher_id" : "210878771", "tweet_amount_of_likes" : "", "tweet_amount_of_comments" : "" }
{ "_id" : { "$oid" : "5bb9c7f0f5e0a646939a4009" }, "tweet_text" : "\"¿Cómo pudo desaparecer de un día para otro un artefacto tan grande?\". España se enfrenta una indemnización de 153.000 euros por la inexplicable desaparición del helicóptero. Esta es la historia http:// ow.ly/selD30m89jC &nbsp;", "snapshot_timestamp" : "Sun Oct 07 08:46:39 +0000 2018", "snapshot_id" : 37, "retweet_count" : "", "id_tweet" : "1048849172961611777", "publisher_screen_name" : "el_pais", "bot_screen_name" : "tiagosi65456343", "impression_order" : 7, "tweet_created_at" : "1:15 AM - 7 Oct 2018", "publisher_id" : "7996082", "tweet_amount_of_likes" : "", "tweet_amount_of_comments" : "" }
{ "_id" : { "$oid" : "5bb9c7f0f5e0a646939a400a" }, "tweet_text" : "Italia y Alemania sustituyeron en el protagonismo a Francia, México y Checoslovaquia. Los años de plomo; por Joaquín Estefanía https:// elpais.com/elpais/2018/10 /04/opinion/1538662142_040780.html?id_externo_rsoc=TW_CC &nbsp; … vía @ el_pais", "snapshot_timestamp" : "Sun Oct 07 08:46:39 +0000 2018", "snapshot_id" : 37, "retweet_count" : "", "id_tweet" : "1048846214979043329", "publisher_screen_name" : "EstefaniaJoaq", "bot_screen_name" : "tiagosi65456343", "impression_order" : 8, "tweet_created_at" : "1:03 AM - 7 Oct 2018", "publisher_id" : "3299116330", "tweet_amount_of_likes" : "", "tweet_amount_of_comments" : "" }
{ "_id" : { "$oid" : "5bb9c7f0f5e0a646939a400b" }, "tweet_text" : "Cães podem ser uma das maiores ameaças à vida selvagem https:// bbc.in/2y3yzgI &nbsp; pic.twitter.com/ePMxGJaJop", "snapshot_timestamp" : "Sun Oct 07 08:46:39 +0000 2018", "snapshot_id" : 37, "retweet_count" : "", "id_tweet" : "1048846672477007874", "publisher_screen_name" : "bbcbrasil", "bot_screen_name" : "tiagosi65456343", "impression_order" : 9, "tweet_created_at" : "1:05 AM - 7 Oct 2018", "publisher_id" : "790680", "tweet_amount_of_likes" : "", "tweet_amount_of_comments" : "" }
{ "_id" : { "$oid" : "5bb9c7f1f5e0a646939a400c" }, "tweet_text" : "El presunto asesino de Girona tenía denuncias previas por violencia de género y una orden de alejamiento de su esposa a la que mató el sábado. También atropelló a la hija de la víctima. El cadáver del hombre fue encontrado horas más tardes http:// ow.ly/hYta30m89bu &nbsp;", "snapshot_timestamp" : "Sun Oct 07 08:46:39 +0000 2018", "snapshot_id" : 37, "retweet_count" : "", "id_tweet" : "1048846651631329282", "publisher_screen_name" : "el_pais", "bot_screen_name" : "tiagosi65456343", "impression_order" : 10, "tweet_created_at" : "1:05 AM - 7 Oct 2018", "publisher_id" : "7996082", "tweet_amount_of_likes" : "", "tweet_amount_of_comments" : "" }
{ "_id" : { "$oid" : "5bb9c7f1f5e0a646939a400d" }, "tweet_text" : "O que faz dos holandeses as pessoas mais altas do mundo https:// bbc.in/2y4p6pk &nbsp; pic.twitter.com/g2aQOdLZbV", "snapshot_timestamp" : "Sun Oct 07 08:46:39 +0000 2018", "snapshot_id" : 37, "retweet_count" : "", "id_tweet" : "1048845418862469120", "publisher_screen_name" : "bbcbrasil", "bot_screen_name" : "tiagosi65456343", "impression_order" : 11, "tweet_created_at" : "1:00 AM - 7 Oct 2018", "publisher_id" : "790680", "tweet_amount_of_likes" : "", "tweet_amount_of_comments" : "" }
{ "_id" : { "$oid" : "5bb9c7f1f5e0a646939a400e" }, "tweet_text" : "Botafogo: o bairro que não para de ganhar novidades: https:// glo.bo/2pECxaN &nbsp; pic.twitter.com/tup9xLG3LN", "snapshot_timestamp" : "Sun Oct 07 08:46:39 +0000 2018", "snapshot_id" : 37, "retweet_count" : "", "id_tweet" : "1048845384875880449", "publisher_screen_name" : "JornalOGlobo", "bot_screen_name" : "tiagosi65456343", "impression_order" : 12, "tweet_created_at" : "1:00 AM - 7 Oct 2018", "publisher_id" : "54341363", "tweet_amount_of_likes" : "", "tweet_amount_of_comments" : "" }
{ "_id" : { "$oid" : "5bb9c7f1f5e0a646939a400f" }, "tweet_text" : "&gt; @ EstadaoSaoPaulo Ex-prefeito de Pompeia condenado por 182 dispensas ilegais de licitação http:// bit.ly/2ytvVjR &nbsp;", "snapshot_timestamp" : "Sun Oct 07 08:46:39 +0000 2018", "snapshot_id" : 37, "retweet_count" : "", "id_tweet" : "1048845381671432192", "publisher_screen_name" : "Estadao", "bot_screen_name" : "tiagosi65456343", "impression_order" : 13, "tweet_created_at" : "1:00 AM - 7 Oct 2018", "publisher_id" : "9317502", "tweet_amount_of_likes" : "", "tweet_amount_of_comments" : "" }
{ "_id" : { "$oid" : "5bb9c7f1f5e0a646939a4010" }, "tweet_text" : "El sábado por la tarde The Walking Dead anunció el regreso de Hershel para despedir a Andrew Lincoln. Solo horas más tarde, fallecía su intérprete, Scott Wilson. Este será su último trabajo tras una carrera de 50 años en algunas películas icónicas http:// ow.ly/IHyS30m89a9 &nbsp;", "snapshot_timestamp" : "Sun Oct 07 08:46:39 +0000 2018", "snapshot_id" : 37, "retweet_count" : "", "id_tweet" : "1048843329365057537", "publisher_screen_name" : "quintatemporada", "bot_screen_name" : "tiagosi65456343", "impression_order" : 14, "tweet_created_at" : "12:51 AM - 7 Oct 2018", "publisher_id" : "250043091", "tweet_amount_of_likes" : "", "tweet_amount_of_comments" : "" }
{ "_id" : { "$oid" : "5bb9c7f1f5e0a646939a4011" }, "tweet_text" : "La activista egipcia Amal Fathy acaba de ser condenada a dos años de cárcel y 500€ de multa por denunciar que fue acosada en su banco y que el Gobierno no ataja el problema # MeToo . Y no es la única historia http:// ow.ly/cMru30m896c &nbsp;", "snapshot_timestamp" : "Sun Oct 07 08:46:39 +0000 2018", "snapshot_id" : 37, "retweet_count" : "", "id_tweet" : "1048844133929025538", "publisher_screen_name" : "el_pais", "bot_screen_name" : "tiagosi65456343", "impression_order" : 15, "tweet_created_at" : "12:55 AM - 7 Oct 2018", "publisher_id" : "7996082", "tweet_amount_of_likes" : "", "tweet_amount_of_comments" : "" }
{ "_id" : { "$oid" : "5bb9c7f2f5e0a646939a4012" }, "tweet_text" : "Os números destas eleições que ajudarão a decidir o futuro do país https:// bbc.in/2y4vjl3 &nbsp; pic.twitter.com/OZXFw7G5NN", "snapshot_timestamp" : "Sun Oct 07 08:46:39 +0000 2018", "snapshot_id" : 37, "retweet_count" : "", "id_tweet" : "1048843158367457281", "publisher_screen_name" : "bbcbrasil", "bot_screen_name" : "tiagosi65456343", "impression_order" : 16, "tweet_created_at" : "12:51 AM - 7 Oct 2018", "publisher_id" : "790680", "tweet_amount_of_likes" : "", "tweet_amount_of_comments" : "" }
{ "_id" : { "$oid" : "5bb9c7f2f5e0a646939a4013" }, "tweet_text" : "El Gobierno planea un impuesto del 0,2% a la compra de acciones https:// elpais.com/economia/2018/ 10/05/actualidad/1538768392_773536.html?id_externo_rsoc=TW_CC &nbsp; … vía @ elpais_economia", "snapshot_timestamp" : "Sun Oct 07 08:46:39 +0000 2018", "snapshot_id" : 37, "retweet_count" : "", "id_tweet" : "1048839828887015424", "publisher_screen_name" : "antonio_maqueda", "bot_screen_name" : "tiagosi65456343", "impression_order" : 17, "tweet_created_at" : "12:37 AM - 7 Oct 2018", "publisher_id" : "267311504", "tweet_amount_of_likes" : "", "tweet_amount_of_comments" : "" }
{ "_id" : { "$oid" : "5bb9c7f2f5e0a646939a4014" }, "tweet_text" : "“Yo no me consideraba un drogadicto. Creía que esos eran los que se clavaban agujas en el brazo, pero en realidad yo era el mayor yonqui. Estuve muy cerca de morir” http:// ow.ly/8dYN30m893H &nbsp;", "snapshot_timestamp" : "Sun Oct 07 08:46:39 +0000 2018", "snapshot_id" : 37, "retweet_count" : "", "id_tweet" : "1048841054991134720", "publisher_screen_name" : "el_pais", "bot_screen_name" : "tiagosi65456343", "impression_order" : 18, "tweet_created_at" : "12:42 AM - 7 Oct 2018", "publisher_id" : "7996082", "tweet_amount_of_likes" : "", "tweet_amount_of_comments" : "" }
{ "_id" : { "$oid" : "5bb9c7f2f5e0a646939a4015" }, "tweet_text" : "# MaisLidas Jovem que trabalhava em alto-mar fica à deriva por 49 dias e sobrevive fazendo fogueiras com madeira retirada da própria embarcação https:// bbc.in/2O2csBj &nbsp; pic.twitter.com/ONAZHM46ck", "snapshot_timestamp" : "Sun Oct 07 08:46:39 +0000 2018", "snapshot_id" : 37, "retweet_count" : "", "id_tweet" : "1048838103945891840", "publisher_screen_name" : "bbcbrasil", "bot_screen_name" : "tiagosi65456343", "impression_order" : 19, "tweet_created_at" : "12:31 AM - 7 Oct 2018", "publisher_id" : "790680", "tweet_amount_of_likes" : "", "tweet_amount_of_comments" : "" }
{ "_id" : { "$oid" : "5bb9c7f2f5e0a646939a4016" }, "tweet_text" : "La gran farsa del padre de Nadia. El fiscal vio tan claro el caso que inclusó sopesó aumentar la pena de los progenitores de la niña http:// ow.ly/ggQP30m88TI &nbsp;", "snapshot_timestamp" : "Sun Oct 07 08:46:39 +0000 2018", "snapshot_id" : 37, "retweet_count" : "", "id_tweet" : "1048838014368206848", "publisher_screen_name" : "el_pais", "bot_screen_name" : "tiagosi65456343", "impression_order" : 20, "tweet_created_at" : "12:30 AM - 7 Oct 2018", "publisher_id" : "7996082", "tweet_amount_of_likes" : "", "tweet_amount_of_comments" : "" }
{ "_id" : { "$oid" : "5bb9c7f2f5e0a646939a4017" }, "tweet_text" : "a gran farsa del padre de Nadia. El fiscal vio tan claro el caso que inclusó sopesó aumentar la pena de los progenitores de la niña http:// ow.ly/ggQP30m88TI &nbsp;", "snapshot_timestamp" : "Sun Oct 07 08:46:39 +0000 2018", "snapshot_id" : 37, "retweet_count" : "", "id_tweet" : "1048837797727989761", "publisher_screen_name" : "el_pais", "bot_screen_name" : "tiagosi65456343", "impression_order" : 21, "tweet_created_at" : "12:29 AM - 7 Oct 2018", "publisher_id" : "7996082", "tweet_amount_of_likes" : "", "tweet_amount_of_comments" : "" }
{ "_id" : { "$oid" : "5bb9c7f2f5e0a646939a4018" }, "tweet_text" : "Hamilton vence GP do Japão e abre 67 pontos de vantagem sobre Vettel https:// www1.folha.uol.com.br/esporte/2018/1 0/hamilton-vence-gp-do-japao-e-abre-67-pontos-de-vantagem-sobre-vettel.shtml?utm_source=twitter&amp;utm_medium=social&amp;utm_campaign=twfolha &nbsp; …", "snapshot_timestamp" : "Sun Oct 07 08:46:39 +0000 2018", "snapshot_id" : 37, "retweet_count" : "", "id_tweet" : "1048836833419960320", "publisher_screen_name" : "folha", "bot_screen_name" : "tiagosi65456343", "impression_order" : 22, "tweet_created_at" : "12:26 AM - 7 Oct 2018", "publisher_id" : "14594813", "tweet_amount_of_likes" : "", "tweet_amount_of_comments" : "" }
{ "_id" : { "$oid" : "5bb9c7f3f5e0a646939a4019" }, "tweet_text" : "Senado americano confirma indicação de Kavanaugh por Trump para a Suprema Corte https:// bbc.in/2PiZI5Y &nbsp; pic.twitter.com/vFYdknjdHv", "snapshot_timestamp" : "Sun Oct 07 08:46:39 +0000 2018", "snapshot_id" : 37, "retweet_count" : "", "id_tweet" : "1048834869021872129", "publisher_screen_name" : "bbcbrasil", "bot_screen_name" : "tiagosi65456343", "impression_order" : 23, "tweet_created_at" : "12:18 AM - 7 Oct 2018", "publisher_id" : "790680", "tweet_amount_of_likes" : "", "tweet_amount_of_comments" : "" }
{ "_id" : { "$oid" : "5bb9c7f3f5e0a646939a401a" }, "tweet_text" : "Alquilar se pone imposible (y no solo por el precio) http:// ow.ly/UWWH30m88Ly &nbsp;", "snapshot_timestamp" : "Sun Oct 07 08:46:39 +0000 2018", "snapshot_id" : 37, "retweet_count" : "", "id_tweet" : "1048834120913227776", "publisher_screen_name" : "el_pais", "bot_screen_name" : "tiagosi65456343", "impression_order" : 24, "tweet_created_at" : "12:15 AM - 7 Oct 2018", "publisher_id" : "7996082", "tweet_amount_of_likes" : "", "tweet_amount_of_comments" : "" }
{ "_id" : { "$oid" : "5bb9c7f3f5e0a646939a401b" }, "tweet_text" : "Novo entrave atrasa plano de trem para ligar região de Campinas a São Paulo https:// www1.folha.uol.com.br/cotidiano/2018 /10/novo-entrave-atrasa-plano-de-trem-para-ligar-regiao-de-campinas-a-sao-paulo.shtml?utm_source=twitter&amp;utm_medium=social&amp;utm_campaign=twfolha &nbsp; …", "snapshot_timestamp" : "Sun Oct 07 08:46:39 +0000 2018", "snapshot_id" : 37, "retweet_count" : "", "id_tweet" : "1048830544698658817", "publisher_screen_name" : "folha", "bot_screen_name" : "tiagosi65456343", "impression_order" : 25, "tweet_created_at" : "12:01 AM - 7 Oct 2018", "publisher_id" : "14594813", "tweet_amount_of_likes" : "", "tweet_amount_of_comments" : "" }
{ "_id" : { "$oid" : "5bb9c7f3f5e0a646939a401c" }, "tweet_text" : "Idosos de Curitiba usam a dança para desafiar as limitações da idade. O @ reporterbrasil mostrou a empolgação do pessoal! Clique pra ver! pic.twitter.com/CJTfLtAw3o", "snapshot_timestamp" : "Sun Oct 07 08:46:39 +0000 2018", "snapshot_id" : 37, "retweet_count" : "", "id_tweet" : "1048830283636723712", "publisher_screen_name" : "ebcnarede", "bot_screen_name" : "tiagosi65456343", "impression_order" : 26, "tweet_created_at" : "12:00 AM - 7 Oct 2018", "publisher_id" : "421268817", "tweet_amount_of_likes" : "", "tweet_amount_of_comments" : "" }
{ "_id" : { "$oid" : "5bb9c7f3f5e0a646939a401d" }, "tweet_text" : "&gt; @ esportefera Ex-jogador de basquete Paul Pierce acredita que a Terra é plana e explica o motivo http:// bit.ly/2yktgIV &nbsp; pic.twitter.com/XJoihzx92s", "snapshot_timestamp" : "Sun Oct 07 08:46:39 +0000 2018", "snapshot_id" : 37, "retweet_count" : "", "id_tweet" : "1048830283527741441", "publisher_screen_name" : "Estadao", "bot_screen_name" : "tiagosi65456343", "impression_order" : 27, "tweet_created_at" : "12:00 AM - 7 Oct 2018", "publisher_id" : "9317502", "tweet_amount_of_likes" : "", "tweet_amount_of_comments" : "" }
{ "_id" : { "$oid" : "5bb9c7f3f5e0a646939a401e" }, "tweet_text" : "Flamengo confirma lesão na coxa de Diego: https:// glo.bo/2pC6AQm &nbsp; pic.twitter.com/QMfls0cKrl", "snapshot_timestamp" : "Sun Oct 07 08:46:39 +0000 2018", "snapshot_id" : 37, "retweet_count" : "", "id_tweet" : "1048830282953121798", "publisher_screen_name" : "JornalOGlobo", "bot_screen_name" : "tiagosi65456343", "impression_order" : 28, "tweet_created_at" : "12:00 AM - 7 Oct 2018", "publisher_id" : "54341363", "tweet_amount_of_likes" : "", "tweet_amount_of_comments" : "" }
{ "_id" : { "$oid" : "5bb9d604f5e0a646939a4020" }, "tweet_text" : "La batalla de Casado y Rivera por liderar la oposición y encarnar la mano dura en Cataluña provoca una escalada de incongruencias y rectificaciones http:// ow.ly/y03x30m89DR &nbsp;", "snapshot_timestamp" : "Sun Oct 07 09:46:44 +0000 2018", "snapshot_id" : 38, "retweet_count" : "", "id_tweet" : "1048856159757721601", "publisher_screen_name" : "el_pais", "bot_screen_name" : "tiagosi65456343", "impression_order" : 0, "tweet_created_at" : "1:42 AM - 7 Oct 2018", "publisher_id" : "7996082", "tweet_amount_of_likes" : "", "tweet_amount_of_comments" : "" }
{ "_id" : { "$oid" : "5bb9d604f5e0a646939a4021" }, "tweet_text" : "Exposição a germes na infância aumenta chances de proteger organismo contra alergias, aponta pesquisa # saúde # alergia # pediatria https:// bbc.in/2yajbhG &nbsp; pic.twitter.com/HqUDCxoVEa", "snapshot_timestamp" : "Sun Oct 07 09:46:44 +0000 2018", "snapshot_id" : 38, "retweet_count" : "", "id_tweet" : "1048853449729875968", "publisher_screen_name" : "bbcbrasil", "bot_screen_name" : "tiagosi65456343", "impression_order" : 1, "tweet_created_at" : "1:32 AM - 7 Oct 2018", "publisher_id" : "790680", "tweet_amount_of_likes" : "", "tweet_amount_of_comments" : "" }
{ "_id" : { "$oid" : "5bb9d605f5e0a646939a4022" }, "tweet_text" : "Concurso da ONG SOS Mata Atlântica tem votação das melhores imagens do bioma https:// www1.folha.uol.com.br/ciencia/2018/1 0/concurso-da-ong-sos-mata-atlantica-tem-votacao-das-melhores-imagens-do-bioma.shtml?utm_source=twitter&amp;utm_medium=social&amp;utm_campaign=twfolha &nbsp; …", "snapshot_timestamp" : "Sun Oct 07 09:46:44 +0000 2018", "snapshot_id" : 38, "retweet_count" : "", "id_tweet" : "1048853195647328256", "publisher_screen_name" : "folha", "bot_screen_name" : "tiagosi65456343", "impression_order" : 2, "tweet_created_at" : "1:31 AM - 7 Oct 2018", "publisher_id" : "14594813", "tweet_amount_of_likes" : "", "tweet_amount_of_comments" : "" }
{ "_id" : { "$oid" : "5bb9d605f5e0a646939a4023" }, "tweet_text" : "# EleccionesBrasil \"Prefiero que mi hijo muera en un accidente a que ande con un bigotón por ahí\". Estas son algunas de las frases más polémicas del ultraderechista Jair Bolsonaro, candidato presidencial brasileño http:// ow.ly/8XKU30m83Ow &nbsp; pic.twitter.com/B1hGhHBluZ", "snapshot_timestamp" : "Sun Oct 07 09:46:44 +0000 2018", "snapshot_id" : 38, "retweet_count" : "", "id_tweet" : "1048852953531072512", "publisher_screen_name" : "el_pais", "bot_screen_name" : "tiagosi65456343", "impression_order" : 3, "tweet_created_at" : "1:30 AM - 7 Oct 2018", "publisher_id" : "7996082", "tweet_amount_of_likes" : "", "tweet_amount_of_comments" : "" }
{ "_id" : { "$oid" : "5bb9d605f5e0a646939a4024" }, "tweet_text" : "Obra de arte de Banksy se autodestrói após ser vendida por mais de 1 milhão de libras https:// bbc.in/2y5vlcx &nbsp; pic.twitter.com/yiewYnwZ6p", "snapshot_timestamp" : "Sun Oct 07 09:46:44 +0000 2018", "snapshot_id" : 38, "retweet_count" : "", "id_tweet" : "1048852652124250112", "publisher_screen_name" : "bbcbrasil", "bot_screen_name" : "tiagosi65456343", "impression_order" : 4, "tweet_created_at" : "1:28 AM - 7 Oct 2018", "publisher_id" : "790680", "tweet_amount_of_likes" : "", "tweet_amount_of_comments" : "" }
{ "_id" : { "$oid" : "5bb9d605f5e0a646939a4025" }, "tweet_text" : "Favorito no PR, Ratinho Junior se vende como representante do 'novo' https:// www1.folha.uol.com.br/poder/2018/10/ favorito-no-pr-ratinho-junior-se-vende-como-representante-do-novo.shtml?utm_source=twitter&amp;utm_medium=social&amp;utm_campaign=twfolha &nbsp; …", "snapshot_timestamp" : "Sun Oct 07 09:46:44 +0000 2018", "snapshot_id" : 38, "retweet_count" : "", "id_tweet" : "1048850929762619392", "publisher_screen_name" : "folha", "bot_screen_name" : "tiagosi65456343", "impression_order" : 5, "tweet_created_at" : "1:22 AM - 7 Oct 2018", "publisher_id" : "14594813", "tweet_amount_of_likes" : "", "tweet_amount_of_comments" : "" }
{ "_id" : { "$oid" : "5bb9d608f5e0a646939a4026" }, "tweet_text" : "Cães podem ser uma das maiores ameaças à vida selvagem https:// bbc.in/2y3yzgI &nbsp; pic.twitter.com/ePMxGJaJop", "snapshot_timestamp" : "Sun Oct 07 09:46:44 +0000 2018", "snapshot_id" : 38, "retweet_count" : "", "id_tweet" : "1048846672477007874", "publisher_screen_name" : "bbcbrasil", "bot_screen_name" : "tiagosi65456343", "impression_order" : 6, "tweet_created_at" : "1:05 AM - 7 Oct 2018", "publisher_id" : "790680", "tweet_amount_of_likes" : "", "tweet_amount_of_comments" : "" }
{ "_id" : { "$oid" : "5bb9d608f5e0a646939a4027" }, "tweet_text" : "&gt; @ EstadaoSaoPaulo Ex-prefeito de Pompeia condenado por 182 dispensas ilegais de licitação http:// bit.ly/2ytvVjR &nbsp;", "snapshot_timestamp" : "Sun Oct 07 09:46:44 +0000 2018", "snapshot_id" : 38, "retweet_count" : "", "id_tweet" : "1048845381671432192", "publisher_screen_name" : "Estadao", "bot_screen_name" : "tiagosi65456343", "impression_order" : 7, "tweet_created_at" : "1:00 AM - 7 Oct 2018", "publisher_id" : "9317502", "tweet_amount_of_likes" : "", "tweet_amount_of_comments" : "" }
{ "_id" : { "$oid" : "5bb9d608f5e0a646939a4028" }, "tweet_text" : "Os números destas eleições que ajudarão a decidir o futuro do país https:// bbc.in/2y4vjl3 &nbsp; pic.twitter.com/OZXFw7G5NN", "snapshot_timestamp" : "Sun Oct 07 09:46:44 +0000 2018", "snapshot_id" : 38, "retweet_count" : "", "id_tweet" : "1048843158367457281", "publisher_screen_name" : "bbcbrasil", "bot_screen_name" : "tiagosi65456343", "impression_order" : 8, "tweet_created_at" : "12:51 AM - 7 Oct 2018", "publisher_id" : "790680", "tweet_amount_of_likes" : "", "tweet_amount_of_comments" : "" }
{ "_id" : { "$oid" : "5bb9d608f5e0a646939a4029" }, "tweet_text" : "# MaisLidas Jovem que trabalhava em alto-mar fica à deriva por 49 dias e sobrevive fazendo fogueiras com madeira retirada da própria embarcação https:// bbc.in/2O2csBj &nbsp; pic.twitter.com/ONAZHM46ck", "snapshot_timestamp" : "Sun Oct 07 09:46:44 +0000 2018", "snapshot_id" : 38, "retweet_count" : "", "id_tweet" : "1048838103945891840", "publisher_screen_name" : "bbcbrasil", "bot_screen_name" : "tiagosi65456343", "impression_order" : 9, "tweet_created_at" : "12:31 AM - 7 Oct 2018", "publisher_id" : "790680", "tweet_amount_of_likes" : "", "tweet_amount_of_comments" : "" }
{ "_id" : { "$oid" : "5bb9d608f5e0a646939a402a" }, "tweet_text" : "a gran farsa del padre de Nadia. El fiscal vio tan claro el caso que inclusó sopesó aumentar la pena de los progenitores de la niña http:// ow.ly/ggQP30m88TI &nbsp;", "snapshot_timestamp" : "Sun Oct 07 09:46:44 +0000 2018", "snapshot_id" : 38, "retweet_count" : "", "id_tweet" : "1048837797727989761", "publisher_screen_name" : "el_pais", "bot_screen_name" : "tiagosi65456343", "impression_order" : 10, "tweet_created_at" : "12:29 AM - 7 Oct 2018", "publisher_id" : "7996082", "tweet_amount_of_likes" : "", "tweet_amount_of_comments" : "" }
{ "_id" : { "$oid" : "5bb9d608f5e0a646939a402b" }, "tweet_text" : "Hamilton vence GP do Japão e abre 67 pontos de vantagem sobre Vettel https:// www1.folha.uol.com.br/esporte/2018/1 0/hamilton-vence-gp-do-japao-e-abre-67-pontos-de-vantagem-sobre-vettel.shtml?utm_source=twitter&amp;utm_medium=social&amp;utm_campaign=twfolha &nbsp; …", "snapshot_timestamp" : "Sun Oct 07 09:46:44 +0000 2018", "snapshot_id" : 38, "retweet_count" : "", "id_tweet" : "1048836833419960320", "publisher_screen_name" : "folha", "bot_screen_name" : "tiagosi65456343", "impression_order" : 11, "tweet_created_at" : "12:26 AM - 7 Oct 2018", "publisher_id" : "14594813", "tweet_amount_of_likes" : "", "tweet_amount_of_comments" : "" }
{ "_id" : { "$oid" : "5bb9d609f5e0a646939a402c" }, "tweet_text" : "Senado americano confirma indicação de Kavanaugh por Trump para a Suprema Corte https:// bbc.in/2PiZI5Y &nbsp; pic.twitter.com/vFYdknjdHv", "snapshot_timestamp" : "Sun Oct 07 09:46:44 +0000 2018", "snapshot_id" : 38, "retweet_count" : "", "id_tweet" : "1048834869021872129", "publisher_screen_name" : "bbcbrasil", "bot_screen_name" : "tiagosi65456343", "impression_order" : 12, "tweet_created_at" : "12:18 AM - 7 Oct 2018", "publisher_id" : "790680", "tweet_amount_of_likes" : "", "tweet_amount_of_comments" : "" }
{ "_id" : { "$oid" : "5bb9d609f5e0a646939a402d" }, "tweet_text" : "Novo entrave atrasa plano de trem para ligar região de Campinas a São Paulo https:// www1.folha.uol.com.br/cotidiano/2018 /10/novo-entrave-atrasa-plano-de-trem-para-ligar-regiao-de-campinas-a-sao-paulo.shtml?utm_source=twitter&amp;utm_medium=social&amp;utm_campaign=twfolha &nbsp; …", "snapshot_timestamp" : "Sun Oct 07 09:46:44 +0000 2018", "snapshot_id" : 38, "retweet_count" : "", "id_tweet" : "1048830544698658817", "publisher_screen_name" : "folha", "bot_screen_name" : "tiagosi65456343", "impression_order" : 13, "tweet_created_at" : "12:01 AM - 7 Oct 2018", "publisher_id" : "14594813", "tweet_amount_of_likes" : "", "tweet_amount_of_comments" : "" }
{ "_id" : { "$oid" : "5bb9e41cf5e0a646939a403f" }, "tweet_text" : "Albert Riverá viajará la semana que viene cuatro días a Colombia http:// ow.ly/Owb130m89Of &nbsp;", "snapshot_timestamp" : "Sun Oct 07 10:46:52 +0000 2018", "snapshot_id" : 39, "retweet_count" : "37", "id_tweet" : "1048859897297887233", "publisher_screen_name" : "el_pais", "bot_screen_name" : "tiagosi65456343", "impression_order" : 1, "tweet_created_at" : "1:57 AM - 7 Oct 2018", "publisher_id" : "7996082", "tweet_amount_of_likes" : "37", "tweet_amount_of_comments" : "37" }
{ "_id" : { "$oid" : "5bb9e41cf5e0a646939a4040" }, "tweet_text" : "Bom dia! Esta é a capa do Correio Braziliense deste domingo, 7 de outubro. Mais de 2 milhões de brasilienses vão as urnas hoje. E ainda, conheça eleitores que escolheram seus candidatos sem repúdio ao adversário pic.twitter.com/ey0dJ4Z10Z", "snapshot_timestamp" : "Sun Oct 07 10:46:52 +0000 2018", "snapshot_id" : 39, "retweet_count" : "2", "id_tweet" : "1048862580696072193", "publisher_screen_name" : "correio", "bot_screen_name" : "tiagosi65456343", "impression_order" : 2, "tweet_created_at" : "2:08 AM - 7 Oct 2018", "publisher_id" : "67150902", "tweet_amount_of_likes" : "2", "tweet_amount_of_comments" : "2" }
{ "_id" : { "$oid" : "5bb9e41df5e0a646939a4041" }, "tweet_text" : "Zé Pilintra é o pai dos desprovidos. # DiálogosdaFé http:// bit.ly/2QwpJyD &nbsp;", "snapshot_timestamp" : "Sun Oct 07 10:46:52 +0000 2018", "snapshot_id" : 39, "retweet_count" : "2", "id_tweet" : "1048864262200934400", "publisher_screen_name" : "cartacapital", "bot_screen_name" : "tiagosi65456343", "impression_order" : 3, "tweet_created_at" : "2:15 AM - 7 Oct 2018", "publisher_id" : "16632084", "tweet_amount_of_likes" : "2", "tweet_amount_of_comments" : "2" }
{ "_id" : { "$oid" : "5bb9e41df5e0a646939a4042" }, "tweet_text" : "Bolsonaro tenta se docilizar para diminuir alta taxa de rejeição https:// www1.folha.uol.com.br/poder/2018/10/ bolsonaro-tenta-se-docilizar-para-diminuir-alta-taxa-de-rejeicao.shtml?utm_source=twitter&amp;utm_medium=social&amp;utm_campaign=twfolha &nbsp; …", "snapshot_timestamp" : "Sun Oct 07 10:46:52 +0000 2018", "snapshot_id" : 39, "retweet_count" : "38", "id_tweet" : "1048859989455134720", "publisher_screen_name" : "folha", "bot_screen_name" : "tiagosi65456343", "impression_order" : 4, "tweet_created_at" : "1:58 AM - 7 Oct 2018", "publisher_id" : "14594813", "tweet_amount_of_likes" : "38", "tweet_amount_of_comments" : "38" }
{ "_id" : { "$oid" : "5bb9e43bf5e0a646939a4043" }, "tweet_text" : "Idosos de Curitiba usam a dança para desafiar as limitações da idade. O @ reporterbrasil mostrou a empolgação do pessoal! Clique pra ver! pic.twitter.com/CJTfLtAw3o", "snapshot_timestamp" : "Sun Oct 07 10:46:52 +0000 2018", "snapshot_id" : 39, "retweet_count" : "", "id_tweet" : "1048830283636723712", "publisher_screen_name" : "ebcnarede", "bot_screen_name" : "tiagosi65456343", "impression_order" : 5, "tweet_created_at" : "12:00 AM - 7 Oct 2018", "publisher_id" : "421268817", "tweet_amount_of_likes" : "", "tweet_amount_of_comments" : "" }
{ "_id" : { "$oid" : "5bb9e43bf5e0a646939a4044" }, "tweet_text" : "Em vídeos, PSL tenta reforçar ideia de que Bolsonaro ganhará em 1º turno. @ PSL_Nacional @ jairbolsonaro # eleições2018 https:// poder360.com.br/eleicoes/em-vi deos-psl-tenta-reforcar-ideia-de-que-bolsonaro-ganhara-em-1o-turno/ &nbsp; … pic.twitter.com/acfvBXGka9", "snapshot_timestamp" : "Sun Oct 07 10:46:52 +0000 2018", "snapshot_id" : 39, "retweet_count" : "", "id_tweet" : "1048863031227297792", "publisher_screen_name" : "Poder360", "bot_screen_name" : "tiagosi65456343", "impression_order" : 6, "tweet_created_at" : "2:10 AM - 7 Oct 2018", "publisher_id" : "4896510833", "tweet_amount_of_likes" : "", "tweet_amount_of_comments" : "" }
{ "_id" : { "$oid" : "5bb9e43bf5e0a646939a4046" }, "tweet_text" : "El sábado por la tarde The Walking Dead anunció el regreso de Hershel para despedir a Andrew Lincoln. Solo horas más tarde, fallecía su intérprete, Scott Wilson. Este será su último trabajo tras una carrera de 50 años en algunas películas icónicas http:// ow.ly/IHyS30m89a9 &nbsp;", "snapshot_timestamp" : "Sun Oct 07 10:46:52 +0000 2018", "snapshot_id" : 39, "retweet_count" : "1", "id_tweet" : "1048843329365057537", "publisher_screen_name" : "quintatemporada", "bot_screen_name" : "tiagosi65456343", "impression_order" : 8, "tweet_created_at" : "12:51 AM - 7 Oct 2018", "publisher_id" : "250043091", "tweet_amount_of_likes" : "1", "tweet_amount_of_comments" : "1" }
{ "_id" : { "$oid" : "5bb9e43cf5e0a646939a4047" }, "tweet_text" : "AO VIVO: acompanhe em tempo real o dia de votação e as notícias das eleições no DF http:// bit.ly/2RwpYuU &nbsp; pic.twitter.com/HkGHfJrzh3", "snapshot_timestamp" : "Sun Oct 07 10:46:52 +0000 2018", "snapshot_id" : 39, "retweet_count" : "", "id_tweet" : "1048868032586502145", "publisher_screen_name" : "correio", "bot_screen_name" : "tiagosi65456343", "impression_order" : 9, "tweet_created_at" : "2:30 AM - 7 Oct 2018", "publisher_id" : "67150902", "tweet_amount_of_likes" : "", "tweet_amount_of_comments" : "" }
{ "_id" : { "$oid" : "5bb9e43cf5e0a646939a4048" }, "tweet_text" : "Los que devolvieron el gasto de las ‘black’ se libran de prisión aunque derrocharan https:// elpais.com/economia/2018/ 10/04/actualidad/1538681752_014547.html &nbsp; …", "snapshot_timestamp" : "Sun Oct 07 10:46:52 +0000 2018", "snapshot_id" : 39, "retweet_count" : "6", "id_tweet" : "1048849402838831104", "publisher_screen_name" : "idebarron", "bot_screen_name" : "tiagosi65456343", "impression_order" : 10, "tweet_created_at" : "1:15 AM - 7 Oct 2018", "publisher_id" : "210878771", "tweet_amount_of_likes" : "6", "tweet_amount_of_comments" : "6" }
{ "_id" : { "$oid" : "5bb9e43cf5e0a646939a4049" }, "tweet_text" : "El Gobierno planea un impuesto del 0,2% a la compra de acciones https:// elpais.com/economia/2018/ 10/05/actualidad/1538768392_773536.html?id_externo_rsoc=TW_CC &nbsp; … vía @ elpais_economia", "snapshot_timestamp" : "Sun Oct 07 10:46:52 +0000 2018", "snapshot_id" : 39, "retweet_count" : "9", "id_tweet" : "1048839828887015424", "publisher_screen_name" : "antonio_maqueda", "bot_screen_name" : "tiagosi65456343", "impression_order" : 11, "tweet_created_at" : "12:37 AM - 7 Oct 2018", "publisher_id" : "267311504", "tweet_amount_of_likes" : "9", "tweet_amount_of_comments" : "9" }
{ "_id" : { "$oid" : "5bb9e43df5e0a646939a404a" }, "tweet_text" : "CAPA: Bolsonaro sobe e atinge 41% dos válidos; Haddad tem 25%. Veja mais: http:// bit.ly/2NnWjkt &nbsp; # estadao pic.twitter.com/NVi8nOcpBa", "snapshot_timestamp" : "Sun Oct 07 10:46:52 +0000 2018", "snapshot_id" : 39, "retweet_count" : "16", "id_tweet" : "1048865514615783424", "publisher_screen_name" : "Estadao", "bot_screen_name" : "tiagosi65456343", "impression_order" : 12, "tweet_created_at" : "2:20 AM - 7 Oct 2018", "publisher_id" : "9317502", "tweet_amount_of_likes" : "16", "tweet_amount_of_comments" : "16" }
{ "_id" : { "$oid" : "5bb9e43df5e0a646939a404b" }, "tweet_text" : "En la concentración de @ espanaciudadana los manifestantes corean vivas a la Guardia Civil, a la policía y al Ejército. \"Estas calles también son nuestras\", claman https://www. google.es/amp/s/elpais.c om/ccaa/2018/10/05/catalunya/1538726821_082779.amp.html &nbsp; … pic.twitter.com/va5Bp6irBD", "snapshot_timestamp" : "Sun Oct 07 10:46:52 +0000 2018", "snapshot_id" : 39, "retweet_count" : "1", "id_tweet" : "1048866835616190464", "publisher_screen_name" : "jcatafiguls", "bot_screen_name" : "tiagosi65456343", "impression_order" : 13, "tweet_created_at" : "2:25 AM - 7 Oct 2018", "publisher_id" : "300748642", "tweet_amount_of_likes" : "1", "tweet_amount_of_comments" : "1" }
{ "_id" : { "$oid" : "5bb9e43df5e0a646939a404d" }, "tweet_text" : "La gran farsa del padre de Nadia | Sociedad | EL PAÍS https:// elpais.com/sociedad/2018/ 10/06/actualidad/1538837231_870023.html &nbsp; …", "snapshot_timestamp" : "Sun Oct 07 10:46:52 +0000 2018", "snapshot_id" : 39, "retweet_count" : "", "id_tweet" : "1048866845514760193", "publisher_screen_name" : "jesusgbueno", "bot_screen_name" : "tiagosi65456343", "impression_order" : 15, "tweet_created_at" : "2:25 AM - 7 Oct 2018", "publisher_id" : "227769858", "tweet_amount_of_likes" : "", "tweet_amount_of_comments" : "" }
{ "_id" : { "$oid" : "5bb9e43df5e0a646939a404e" }, "tweet_text" : "Tristeza, raiva, medo: como se proteger dos sentimentos ruins nestas eleições https:// bbc.in/2Pe1mFW &nbsp; pic.twitter.com/QqsqC07DHs", "snapshot_timestamp" : "Sun Oct 07 10:46:52 +0000 2018", "snapshot_id" : 39, "retweet_count" : "4", "id_tweet" : "1048858907425292288", "publisher_screen_name" : "bbcbrasil", "bot_screen_name" : "tiagosi65456343", "impression_order" : 16, "tweet_created_at" : "1:53 AM - 7 Oct 2018", "publisher_id" : "790680", "tweet_amount_of_likes" : "4", "tweet_amount_of_comments" : "4" }
{ "_id" : { "$oid" : "5bb9e43df5e0a646939a404f" }, "tweet_text" : "Som Infinito compila obras de Santa Hildegarda de Bingen. Monja beneditina é considerada como a primeira mulher compositora da música ocidental. Ouça daqui a pouco, às 7h, na @ mecfm . https:// bit.ly/2Qutd4J &nbsp; Pixabay pic.twitter.com/ncfDl6bi09", "snapshot_timestamp" : "Sun Oct 07 10:46:52 +0000 2018", "snapshot_id" : 39, "retweet_count" : "", "id_tweet" : "1048860492528144385", "publisher_screen_name" : "ebcnarede", "bot_screen_name" : "tiagosi65456343", "impression_order" : 17, "tweet_created_at" : "2:00 AM - 7 Oct 2018", "publisher_id" : "421268817", "tweet_amount_of_likes" : "", "tweet_amount_of_comments" : "" }
{ "_id" : { "$oid" : "5bb9e43df5e0a646939a4050" }, "tweet_text" : "Italia y Alemania sustituyeron en el protagonismo a Francia, México y Checoslovaquia. Los años de plomo; por Joaquín Estefanía https:// elpais.com/elpais/2018/10 /04/opinion/1538662142_040780.html?id_externo_rsoc=TW_CC &nbsp; … vía @ el_pais", "snapshot_timestamp" : "Sun Oct 07 10:46:52 +0000 2018", "snapshot_id" : 39, "retweet_count" : "", "id_tweet" : "1048846214979043329", "publisher_screen_name" : "EstefaniaJoaq", "bot_screen_name" : "tiagosi65456343", "impression_order" : 18, "tweet_created_at" : "1:03 AM - 7 Oct 2018", "publisher_id" : "3299116330", "tweet_amount_of_likes" : "", "tweet_amount_of_comments" : "" }
{ "_id" : { "$oid" : "5bb9e43ef5e0a646939a4051" }, "tweet_text" : "Governo de MG: Ibope e Datafolha indicam 2º turno com Anastasia na liderança. @ Anastasia # eleições2018 https:// poder360.com.br/pesquisas/gove rno-de-mg-ibope-e-datafolha-indicam-2o-turno-com-anastasia-na-lideranca/ &nbsp; … pic.twitter.com/m4GiunPMZE", "snapshot_timestamp" : "Sun Oct 07 10:46:52 +0000 2018", "snapshot_id" : 39, "retweet_count" : "", "id_tweet" : "1048865851989020672", "publisher_screen_name" : "Poder360", "bot_screen_name" : "tiagosi65456343", "impression_order" : 19, "tweet_created_at" : "2:21 AM - 7 Oct 2018", "publisher_id" : "4896510833", "tweet_amount_of_likes" : "", "tweet_amount_of_comments" : "" }
{ "_id" : { "$oid" : "5bb9e43ef5e0a646939a4052" }, "tweet_text" : "La activista egipcia Amal Fathy acaba de ser condenada a dos años de cárcel y 500€ de multa por denunciar que fue acosada en su banco y que el Gobierno no ataja el problema # MeToo . Y no es la única historia http:// ow.ly/cMru30m896c &nbsp;", "snapshot_timestamp" : "Sun Oct 07 10:46:52 +0000 2018", "snapshot_id" : 39, "retweet_count" : "3", "id_tweet" : "1048844133929025538", "publisher_screen_name" : "el_pais", "bot_screen_name" : "tiagosi65456343", "impression_order" : 20, "tweet_created_at" : "12:55 AM - 7 Oct 2018", "publisher_id" : "7996082", "tweet_amount_of_likes" : "3", "tweet_amount_of_comments" : "3" }
{ "_id" : { "$oid" : "5bb9e43ef5e0a646939a4053" }, "tweet_text" : "Botafogo: o bairro que não para de ganhar novidades: https:// glo.bo/2pECxaN &nbsp; pic.twitter.com/tup9xLG3LN", "snapshot_timestamp" : "Sun Oct 07 10:46:52 +0000 2018", "snapshot_id" : 39, "retweet_count" : "2", "id_tweet" : "1048845384875880449", "publisher_screen_name" : "JornalOGlobo", "bot_screen_name" : "tiagosi65456343", "impression_order" : 21, "tweet_created_at" : "1:00 AM - 7 Oct 2018", "publisher_id" : "54341363", "tweet_amount_of_likes" : "2", "tweet_amount_of_comments" : "2" }
{ "_id" : { "$oid" : "5bb9e43ef5e0a646939a4054" }, "tweet_text" : "La universidad de Salamanca ha dado numerosas frases hechas que seguro que utilizas en tu vida diaria http:// ow.ly/Cow630m8aiA &nbsp;", "snapshot_timestamp" : "Sun Oct 07 10:46:52 +0000 2018", "snapshot_id" : 39, "retweet_count" : "3", "id_tweet" : "1048869299333595136", "publisher_screen_name" : "el_pais", "bot_screen_name" : "tiagosi65456343", "impression_order" : 22, "tweet_created_at" : "2:35 AM - 7 Oct 2018", "publisher_id" : "7996082", "tweet_amount_of_likes" : "3", "tweet_amount_of_comments" : "3" }
{ "_id" : { "$oid" : "5bb9e43ef5e0a646939a4055" }, "tweet_text" : "Como estão os estudos por aí? Falta um mês para as provas do # Enem2018 e a @ RadioagenciaEBC dá dicas para você se preparar.Ouça aqui: http:// bit.ly/2zR8DWQ &nbsp; Marcelo Camargo/Agência Brasil pic.twitter.com/A1mBrJAKb5", "snapshot_timestamp" : "Sun Oct 07 10:46:52 +0000 2018", "snapshot_id" : 39, "retweet_count" : "", "id_tweet" : "1048845384536088576", "publisher_screen_name" : "ebcnarede", "bot_screen_name" : "tiagosi65456343", "impression_order" : 23, "tweet_created_at" : "1:00 AM - 7 Oct 2018", "publisher_id" : "421268817", "tweet_amount_of_likes" : "", "tweet_amount_of_comments" : "" }
{ "_id" : { "$oid" : "5bb9e43ef5e0a646939a4056" }, "tweet_text" : "\"Jair Bolsonaro, machista y racista, además de profundo ignorante sobre cualquier asunto que no conlleve la exhibición de testosterona, es favorito para ganar las elecciones de Brasil\". El análisis de Xosé Hermida http:// ow.ly/qvdb30m89TM &nbsp;", "snapshot_timestamp" : "Sun Oct 07 10:46:52 +0000 2018", "snapshot_id" : 39, "retweet_count" : "17", "id_tweet" : "1048861507335991296", "publisher_screen_name" : "el_pais", "bot_screen_name" : "tiagosi65456343", "impression_order" : 24, "tweet_created_at" : "2:04 AM - 7 Oct 2018", "publisher_id" : "7996082", "tweet_amount_of_likes" : "17", "tweet_amount_of_comments" : "17" }
{ "_id" : { "$oid" : "5bb9e43ff5e0a646939a4057" }, "tweet_text" : "Internet supera TV em influência na eleição https:// www1.folha.uol.com.br/poder/2018/10/ internet-supera-tv-em-influencia-na-eleicao.shtml?utm_source=twitter&amp;utm_medium=social&amp;utm_campaign=twfolha &nbsp; …", "snapshot_timestamp" : "Sun Oct 07 10:46:52 +0000 2018", "snapshot_id" : 39, "retweet_count" : "14", "id_tweet" : "1048864772207337473", "publisher_screen_name" : "folha", "bot_screen_name" : "tiagosi65456343", "impression_order" : 25, "tweet_created_at" : "2:17 AM - 7 Oct 2018", "publisher_id" : "14594813", "tweet_amount_of_likes" : "14", "tweet_amount_of_comments" : "14" }
{ "_id" : { "$oid" : "5bb9e43ff5e0a646939a4058" }, "tweet_text" : "\"¿Cómo pudo desaparecer de un día para otro un artefacto tan grande?\". España se enfrenta una indemnización de 153.000 euros por la inexplicable desaparición del helicóptero. Esta es la historia http:// ow.ly/selD30m89jC &nbsp;", "snapshot_timestamp" : "Sun Oct 07 10:46:52 +0000 2018", "snapshot_id" : 39, "retweet_count" : "4", "id_tweet" : "1048849172961611777", "publisher_screen_name" : "el_pais", "bot_screen_name" : "tiagosi65456343", "impression_order" : 26, "tweet_created_at" : "1:15 AM - 7 Oct 2018", "publisher_id" : "7996082", "tweet_amount_of_likes" : "4", "tweet_amount_of_comments" : "4" }
{ "_id" : { "$oid" : "5bb9e43ff5e0a646939a4059" }, "tweet_text" : "&gt; @ esportefera Ex-jogador de basquete Paul Pierce acredita que a Terra é plana e explica o motivo http:// bit.ly/2yktgIV &nbsp; pic.twitter.com/XJoihzx92s", "snapshot_timestamp" : "Sun Oct 07 10:46:52 +0000 2018", "snapshot_id" : 39, "retweet_count" : "7", "id_tweet" : "1048830283527741441", "publisher_screen_name" : "Estadao", "bot_screen_name" : "tiagosi65456343", "impression_order" : 27, "tweet_created_at" : "12:00 AM - 7 Oct 2018", "publisher_id" : "9317502", "tweet_amount_of_likes" : "7", "tweet_amount_of_comments" : "7" }
{ "_id" : { "$oid" : "5bb9e43ff5e0a646939a405a" }, "tweet_text" : "Na reta final das eleições 2018, você caiu em alguma mensagem falsa de WhatsApp? https:// bbc.in/2PeoJ1V &nbsp; pic.twitter.com/QyCdxJBMGB", "snapshot_timestamp" : "Sun Oct 07 10:46:52 +0000 2018", "snapshot_id" : 39, "retweet_count" : "2", "id_tweet" : "1048868803713662976", "publisher_screen_name" : "bbcbrasil", "bot_screen_name" : "tiagosi65456343", "impression_order" : 28, "tweet_created_at" : "2:33 AM - 7 Oct 2018", "publisher_id" : "790680", "tweet_amount_of_likes" : "2", "tweet_amount_of_comments" : "2" }
{ "_id" : { "$oid" : "5bb9e43ff5e0a646939a405b" }, "tweet_text" : "La gran farsa del padre de Nadia. El fiscal vio tan claro el caso que inclusó sopesó aumentar la pena de los progenitores de la niña http:// ow.ly/ggQP30m88TI &nbsp;", "snapshot_timestamp" : "Sun Oct 07 10:46:52 +0000 2018", "snapshot_id" : 39, "retweet_count" : "7", "id_tweet" : "1048838014368206848", "publisher_screen_name" : "el_pais", "bot_screen_name" : "tiagosi65456343", "impression_order" : 29, "tweet_created_at" : "12:30 AM - 7 Oct 2018", "publisher_id" : "7996082", "tweet_amount_of_likes" : "7", "tweet_amount_of_comments" : "7" }
{ "_id" : { "$oid" : "5bb9f250f5e0a646939a405c" }, "tweet_text" : "Eleitores de Alckmin preferem Haddad a Bolsonaro, diz Datafolha https://www. oantagonista.com/brasil/eleitor es-de-alckmin-preferem-haddad-bolsonaro-diz-datafolha/ &nbsp; …", "snapshot_timestamp" : "Sun Oct 07 11:47:28 +0000 2018", "snapshot_id" : 40, "retweet_count" : "98", "id_tweet" : "1048880898370883584", "publisher_screen_name" : "o_antagonista", "bot_screen_name" : "tiagosi65456343", "impression_order" : 0, "tweet_created_at" : "3:21 AM - 7 Oct 2018", "publisher_id" : "2880932962", "tweet_amount_of_likes" : "98", "tweet_amount_of_comments" : "98" }
{ "_id" : { "$oid" : "5bb9f250f5e0a646939a405e" }, "tweet_text" : "Bolsonaro é um Collor mais raivoso. Haddad reencarna o trabalhismo. Salvo mudanças de última hora, este será o confronto | http:// bit.ly/2zTGXAI &nbsp;", "snapshot_timestamp" : "Sun Oct 07 11:47:28 +0000 2018", "snapshot_id" : 40, "retweet_count" : "26", "id_tweet" : "1048879366611132417", "publisher_screen_name" : "cartacapital", "bot_screen_name" : "tiagosi65456343", "impression_order" : 2, "tweet_created_at" : "3:15 AM - 7 Oct 2018", "publisher_id" : "16632084", "tweet_amount_of_likes" : "26", "tweet_amount_of_comments" : "26" }
{ "_id" : { "$oid" : "5bb9f250f5e0a646939a405f" }, "tweet_text" : "É hoje! Confira o guia com informações essenciais sobre os candidatos e vote consciente # Eleicoes2018 http:// bit.ly/2EcuSdQ &nbsp;", "snapshot_timestamp" : "Sun Oct 07 11:47:28 +0000 2018", "snapshot_id" : 40, "retweet_count" : "", "id_tweet" : "1048887081076969475", "publisher_screen_name" : "congemfoco", "bot_screen_name" : "tiagosi65456343", "impression_order" : 3, "tweet_created_at" : "3:45 AM - 7 Oct 2018", "publisher_id" : "47754867", "tweet_amount_of_likes" : "", "tweet_amount_of_comments" : "" }
{ "_id" : { "$oid" : "5bb9f251f5e0a646939a4060" }, "tweet_text" : "80% dos eleitores de Ciro rejeitam Bolsonaro https://www. oantagonista.com/brasil/80-dos- eleitores-de-ciro-rejeitam-bolsonaro/ &nbsp; …", "snapshot_timestamp" : "Sun Oct 07 11:47:28 +0000 2018", "snapshot_id" : 40, "retweet_count" : "101", "id_tweet" : "1048878126762287104", "publisher_screen_name" : "o_antagonista", "bot_screen_name" : "tiagosi65456343", "impression_order" : 4, "tweet_created_at" : "3:10 AM - 7 Oct 2018", "publisher_id" : "2880932962", "tweet_amount_of_likes" : "101", "tweet_amount_of_comments" : "101" }
{ "_id" : { "$oid" : "5bb9f251f5e0a646939a4061" }, "tweet_text" : "&gt; @ ECantanhede 'As duas seitas - O confronto é entre duas seitas, lulistas e bolsonaristas, mas viva a democracia!' http:// bit.ly/2NrPwGn &nbsp; pic.twitter.com/sd0g0mw9Cc", "snapshot_timestamp" : "Sun Oct 07 11:47:28 +0000 2018", "snapshot_id" : 40, "retweet_count" : "138", "id_tweet" : "1048873064228782080", "publisher_screen_name" : "Estadao", "bot_screen_name" : "tiagosi65456343", "impression_order" : 5, "tweet_created_at" : "2:50 AM - 7 Oct 2018", "publisher_id" : "9317502", "tweet_amount_of_likes" : "138", "tweet_amount_of_comments" : "138" }
{ "_id" : { "$oid" : "5bb9f26ff5e0a646939a4062" }, "tweet_text" : "TSE determina que Facebook retire notícias falsas sobre Manuela D’Ávila. @ manueladavila @ TSEjusbr https:// poder360.com.br/eleicoes/tse-d etermina-que-facebook-retire-noticias-falsas-sobre-manuela-davila/ &nbsp; … pic.twitter.com/xg7oB2k3oa", "snapshot_timestamp" : "Sun Oct 07 11:47:28 +0000 2018", "snapshot_id" : 40, "retweet_count" : "1", "id_tweet" : "1048883234262667264", "publisher_screen_name" : "Poder360", "bot_screen_name" : "tiagosi65456343", "impression_order" : 6, "tweet_created_at" : "3:30 AM - 7 Oct 2018", "publisher_id" : "4896510833", "tweet_amount_of_likes" : "1", "tweet_amount_of_comments" : "1" }
{ "_id" : { "$oid" : "5bb9f26ff5e0a646939a4063" }, "tweet_text" : "Após campanha radicalizada, um país dividido vai às urnas. https:// glo.bo/2O9hiN3 &nbsp; pic.twitter.com/lkLMUr8FkY", "snapshot_timestamp" : "Sun Oct 07 11:47:28 +0000 2018", "snapshot_id" : 40, "retweet_count" : "6", "id_tweet" : "1048886671813619714", "publisher_screen_name" : "JornalOGlobo", "bot_screen_name" : "tiagosi65456343", "impression_order" : 7, "tweet_created_at" : "3:44 AM - 7 Oct 2018", "publisher_id" : "54341363", "tweet_amount_of_likes" : "6", "tweet_amount_of_comments" : "6" }
{ "_id" : { "$oid" : "5bb9f26ff5e0a646939a4064" }, "tweet_text" : "Mesário voluntário ou convocado tem a obrigação de comparecer às eleições para trabalhar. http:// huffp.st/ckH0HdX &nbsp;", "snapshot_timestamp" : "Sun Oct 07 11:47:28 +0000 2018", "snapshot_id" : 40, "retweet_count" : "1", "id_tweet" : "1048885402306838528", "publisher_screen_name" : "huffpostbrasil", "bot_screen_name" : "tiagosi65456343", "impression_order" : 8, "tweet_created_at" : "3:39 AM - 7 Oct 2018", "publisher_id" : "1875887166", "tweet_amount_of_likes" : "1", "tweet_amount_of_comments" : "1" }
{ "_id" : { "$oid" : "5bb9f26ff5e0a646939a4065" }, "tweet_text" : "Bolsonaro no primeiro turno https://www. oantagonista.com/brasil/bolsona ro-no-primeiro-turno-3/ &nbsp; …", "snapshot_timestamp" : "Sun Oct 07 11:47:28 +0000 2018", "snapshot_id" : 40, "retweet_count" : "53", "id_tweet" : "1048873411932557312", "publisher_screen_name" : "o_antagonista", "bot_screen_name" : "tiagosi65456343", "impression_order" : 9, "tweet_created_at" : "2:51 AM - 7 Oct 2018", "publisher_id" : "2880932962", "tweet_amount_of_likes" : "53", "tweet_amount_of_comments" : "53" }
{ "_id" : { "$oid" : "5bb9f270f5e0a646939a4066" }, "tweet_text" : "O \"milagre econômico\" não foi tão milagroso. Por Alexander Busch, da DW. # Análise http:// bit.ly/2zThO9k &nbsp;", "snapshot_timestamp" : "Sun Oct 07 11:47:28 +0000 2018", "snapshot_id" : 40, "retweet_count" : "", "id_tweet" : "1048886929784279040", "publisher_screen_name" : "cartacapital", "bot_screen_name" : "tiagosi65456343", "impression_order" : 10, "tweet_created_at" : "3:45 AM - 7 Oct 2018", "publisher_id" : "16632084", "tweet_amount_of_likes" : "", "tweet_amount_of_comments" : "" }
{ "_id" : { "$oid" : "5bb9f270f5e0a646939a4067" }, "tweet_text" : "Maluma: “No quiero vivir mucho tiempo. Cuando comience a estar enfermo, me iré a una isla con mis animales y mi familia. Y elegiré mi final. Y si no es elegido por mí, Dios sabe cómo hará esas cosas” http:// ow.ly/kzY230m8aUr &nbsp;", "snapshot_timestamp" : "Sun Oct 07 11:47:28 +0000 2018", "snapshot_id" : 40, "retweet_count" : "12", "id_tweet" : "1048880636520538114", "publisher_screen_name" : "el_pais", "bot_screen_name" : "tiagosi65456343", "impression_order" : 11, "tweet_created_at" : "3:20 AM - 7 Oct 2018", "publisher_id" : "7996082", "tweet_amount_of_likes" : "12", "tweet_amount_of_comments" : "12" }
{ "_id" : { "$oid" : "5bb9f270f5e0a646939a4068" }, "tweet_text" : "25% dos eleitores que vão às urnas hoje não concluíram o ensino fundamental http:// bit.ly/2OJyfx3 &nbsp; pic.twitter.com/0hdQqWbJep", "snapshot_timestamp" : "Sun Oct 07 11:47:28 +0000 2018", "snapshot_id" : 40, "retweet_count" : "2", "id_tweet" : "1048883290667732992", "publisher_screen_name" : "correio", "bot_screen_name" : "tiagosi65456343", "impression_order" : 12, "tweet_created_at" : "3:30 AM - 7 Oct 2018", "publisher_id" : "67150902", "tweet_amount_of_likes" : "2", "tweet_amount_of_comments" : "2" }
{ "_id" : { "$oid" : "5bb9f270f5e0a646939a4069" }, "tweet_text" : "Escola pública do DF é exemplo de consciência ecológica, os ensinamentos de sala de aula levam benefícios para os moradores da comunidade. Conheça a instituição no @ reporterbrasil . pic.twitter.com/uGlTyDHF90", "snapshot_timestamp" : "Sun Oct 07 11:47:28 +0000 2018", "snapshot_id" : 40, "retweet_count" : "", "id_tweet" : "1048875581998227457", "publisher_screen_name" : "ebcnarede", "bot_screen_name" : "tiagosi65456343", "impression_order" : 13, "tweet_created_at" : "3:00 AM - 7 Oct 2018", "publisher_id" : "421268817", "tweet_amount_of_likes" : "", "tweet_amount_of_comments" : "" }
{ "_id" : { "$oid" : "5bb9f270f5e0a646939a406a" }, "tweet_text" : "Bolsonaro avança no eleitorado lulista https://www. oantagonista.com/brasil/bolsona ro-avanca-no-eleitorado-lulista/ &nbsp; …", "snapshot_timestamp" : "Sun Oct 07 11:47:28 +0000 2018", "snapshot_id" : 40, "retweet_count" : "8", "id_tweet" : "1048885720381882368", "publisher_screen_name" : "o_antagonista", "bot_screen_name" : "tiagosi65456343", "impression_order" : 14, "tweet_created_at" : "3:40 AM - 7 Oct 2018", "publisher_id" : "2880932962", "tweet_amount_of_likes" : "8", "tweet_amount_of_comments" : "8" }
{ "_id" : { "$oid" : "5bb9f270f5e0a646939a406b" }, "tweet_text" : "Paula Ehevarría, sin pelos en las repuestas: https:// elpais.com/elpais/2018/10 /05/gente/1538740651_532296.html &nbsp; …", "snapshot_timestamp" : "Sun Oct 07 11:47:28 +0000 2018", "snapshot_id" : 40, "retweet_count" : "9", "id_tweet" : "1048871705530302465", "publisher_screen_name" : "luzsmellado", "bot_screen_name" : "tiagosi65456343", "impression_order" : 15, "tweet_created_at" : "2:44 AM - 7 Oct 2018", "publisher_id" : "868301383", "tweet_amount_of_likes" : "9", "tweet_amount_of_comments" : "9" }
{ "_id" : { "$oid" : "5bb9f271f5e0a646939a406c" }, "tweet_text" : "Bom dia! Na eleição que ficará marcada pela polarização inédita, mais de 147,3 milhões de brasileiros vão às urnas hoje para escolher pela oitava vez desde a redemocratização o presidente do país, além de governadores, senadores e deputados federais e estaduais. # JornalOGlobo pic.twitter.com/YFIjEYZrd5", "snapshot_timestamp" : "Sun Oct 07 11:47:28 +0000 2018", "snapshot_id" : 40, "retweet_count" : "11", "id_tweet" : "1048884082707451904", "publisher_screen_name" : "JornalOGlobo", "bot_screen_name" : "tiagosi65456343", "impression_order" : 16, "tweet_created_at" : "3:33 AM - 7 Oct 2018", "publisher_id" : "54341363", "tweet_amount_of_likes" : "11", "tweet_amount_of_comments" : "11" }
{ "_id" : { "$oid" : "5bb9f271f5e0a646939a406d" }, "tweet_text" : "La obra de arte se autodestruyó, sin aviso previo, en cinco segundos. El artista británico Banksy ha vuelto a gastar una de sus bromas pesadas al mundo del arte, para denunciar las derivas más absurdas. El comprador había pagado 1,04 millones de libras http:// ow.ly/zAGr30m830i &nbsp; pic.twitter.com/IOoTRdx75a", "snapshot_timestamp" : "Sun Oct 07 11:47:28 +0000 2018", "snapshot_id" : 40, "retweet_count" : "4", "id_tweet" : "1048874195554377729", "publisher_screen_name" : "el_pais", "bot_screen_name" : "tiagosi65456343", "impression_order" : 17, "tweet_created_at" : "2:54 AM - 7 Oct 2018", "publisher_id" : "7996082", "tweet_amount_of_likes" : "4", "tweet_amount_of_comments" : "4" }
{ "_id" : { "$oid" : "5bb9f271f5e0a646939a406e" }, "tweet_text" : "Saiba qual a ordem de votação nas # Eleições2018 http:// bit.ly/2Nv9T5s &nbsp; pic.twitter.com/48i09jtGMb", "snapshot_timestamp" : "Sun Oct 07 11:47:28 +0000 2018", "snapshot_id" : 40, "retweet_count" : "1", "id_tweet" : "1048886905369051137", "publisher_screen_name" : "folha", "bot_screen_name" : "tiagosi65456343", "impression_order" : 18, "tweet_created_at" : "3:45 AM - 7 Oct 2018", "publisher_id" : "14594813", "tweet_amount_of_likes" : "1", "tweet_amount_of_comments" : "1" }
{ "_id" : { "$oid" : "5bb9f271f5e0a646939a406f" }, "tweet_text" : "Spotify sobrevive a los peores augurios https:// elpais.com/tecnologia/201 8/10/05/actualidad/1538741114_562621.html &nbsp; …", "snapshot_timestamp" : "Sun Oct 07 11:47:28 +0000 2018", "snapshot_id" : 40, "retweet_count" : "", "id_tweet" : "1048880909167071232", "publisher_screen_name" : "elpais_tec", "bot_screen_name" : "tiagosi65456343", "impression_order" : 19, "tweet_created_at" : "3:21 AM - 7 Oct 2018", "publisher_id" : "106769240", "tweet_amount_of_likes" : "", "tweet_amount_of_comments" : "" }
{ "_id" : { "$oid" : "5bb9f271f5e0a646939a4070" }, "tweet_text" : "Saiba o que é permitido e proibido aos eleitores no dia da eleição. # eleições2018 https:// poder360.com.br/eleicoes/saiba -o-que-e-permitido-e-proibido-aos-eleitores-no-dia-da-eleicao/ &nbsp; … pic.twitter.com/f22UK7zNBJ", "snapshot_timestamp" : "Sun Oct 07 11:47:28 +0000 2018", "snapshot_id" : 40, "retweet_count" : "1", "id_tweet" : "1048876856081108993", "publisher_screen_name" : "Poder360", "bot_screen_name" : "tiagosi65456343", "impression_order" : 20, "tweet_created_at" : "3:05 AM - 7 Oct 2018", "publisher_id" : "4896510833", "tweet_amount_of_likes" : "1", "tweet_amount_of_comments" : "1" }
{ "_id" : { "$oid" : "5bb9f271f5e0a646939a4071" }, "tweet_text" : "Aquí de charla con Vince Gilligan. Me quedé con ganas de mucho más, es un gusto hablar con este hombre https:// elpais.com/cultura/2018/1 0/01/television/1538393759_076249.html &nbsp; …", "snapshot_timestamp" : "Sun Oct 07 11:47:28 +0000 2018", "snapshot_id" : 40, "retweet_count" : "1", "id_tweet" : "1048872707075571712", "publisher_screen_name" : "cakivi", "bot_screen_name" : "tiagosi65456343", "impression_order" : 21, "tweet_created_at" : "2:48 AM - 7 Oct 2018", "publisher_id" : "16182002", "tweet_amount_of_likes" : "1", "tweet_amount_of_comments" : "1" }
{ "_id" : { "$oid" : "5bb9f272f5e0a646939a4072" }, "tweet_text" : "Evite filas na votação. http:// huffp.st/Kcqqsvt &nbsp;", "snapshot_timestamp" : "Sun Oct 07 11:47:28 +0000 2018", "snapshot_id" : 40, "retweet_count" : "1", "id_tweet" : "1048883387681951744", "publisher_screen_name" : "huffpostbrasil", "bot_screen_name" : "tiagosi65456343", "impression_order" : 22, "tweet_created_at" : "3:31 AM - 7 Oct 2018", "publisher_id" : "1875887166", "tweet_amount_of_likes" : "1", "tweet_amount_of_comments" : "1" }
{ "_id" : { "$oid" : "5bb9f272f5e0a646939a4073" }, "tweet_text" : "&gt; @ fhc 'Hora de voto: Mais do que nunca é preciso insistir em nossos valores, na democracia' http:// bit.ly/2BZVqwo &nbsp; pic.twitter.com/cDkqUhKtSy", "snapshot_timestamp" : "Sun Oct 07 11:47:28 +0000 2018", "snapshot_id" : 40, "retweet_count" : "1", "id_tweet" : "1048887196038705152", "publisher_screen_name" : "Estadao", "bot_screen_name" : "tiagosi65456343", "impression_order" : 23, "tweet_created_at" : "3:46 AM - 7 Oct 2018", "publisher_id" : "9317502", "tweet_amount_of_likes" : "1", "tweet_amount_of_comments" : "1" }
{ "_id" : { "$oid" : "5bb9f272f5e0a646939a4074" }, "tweet_text" : "Las elecciones presidenciales en Brasil 2018 http:// ow.ly/1FCR30m88cF &nbsp;", "snapshot_timestamp" : "Sun Oct 07 11:47:28 +0000 2018", "snapshot_id" : 40, "retweet_count" : "1", "id_tweet" : "1048878109511102465", "publisher_screen_name" : "elpais_america", "bot_screen_name" : "tiagosi65456343", "impression_order" : 24, "tweet_created_at" : "3:10 AM - 7 Oct 2018", "publisher_id" : "1244357988", "tweet_amount_of_likes" : "1", "tweet_amount_of_comments" : "1" }
{ "_id" : { "$oid" : "5bb9f272f5e0a646939a4075" }, "tweet_text" : "Las personas con parálisis cerebral también tienen sexo http:// ow.ly/4K6J30m8bna &nbsp;", "snapshot_timestamp" : "Sun Oct 07 11:47:28 +0000 2018", "snapshot_id" : 40, "retweet_count" : "2", "id_tweet" : "1048884215872466944", "publisher_screen_name" : "el_pais", "bot_screen_name" : "tiagosi65456343", "impression_order" : 25, "tweet_created_at" : "3:34 AM - 7 Oct 2018", "publisher_id" : "7996082", "tweet_amount_of_likes" : "2", "tweet_amount_of_comments" : "2" }
{ "_id" : { "$oid" : "5bb9f272f5e0a646939a4076" }, "tweet_text" : "Mais de 2 milhões de brasilienses vão as urnas hoje; confira dicas http:// bit.ly/2y8lfHN &nbsp; pic.twitter.com/wyjDwLGIZJ", "snapshot_timestamp" : "Sun Oct 07 11:47:28 +0000 2018", "snapshot_id" : 40, "retweet_count" : "1", "id_tweet" : "1048879356343283712", "publisher_screen_name" : "correio", "bot_screen_name" : "tiagosi65456343", "impression_order" : 26, "tweet_created_at" : "3:15 AM - 7 Oct 2018", "publisher_id" : "67150902", "tweet_amount_of_likes" : "1", "tweet_amount_of_comments" : "1" }
{ "_id" : { "$oid" : "5bb9f273f5e0a646939a4077" }, "tweet_text" : "Por que a Constituição brasileira pede que você tenha mais atenção a seu voto para o Congresso https:// bbc.in/2PeTzYg &nbsp; pic.twitter.com/nRGjFgCEm5", "snapshot_timestamp" : "Sun Oct 07 11:47:28 +0000 2018", "snapshot_id" : 40, "retweet_count" : "4", "id_tweet" : "1048873944009396224", "publisher_screen_name" : "bbcbrasil", "bot_screen_name" : "tiagosi65456343", "impression_order" : 27, "tweet_created_at" : "2:53 AM - 7 Oct 2018", "publisher_id" : "790680", "tweet_amount_of_likes" : "4", "tweet_amount_of_comments" : "4" }
{ "_id" : { "$oid" : "5bb9f273f5e0a646939a4078" }, "tweet_text" : "&gt; @ EstadaoPolitica Divisão provoca segundo turno em São Paulo após 16 anos http:// bit.ly/2C2Q8Ao &nbsp;", "snapshot_timestamp" : "Sun Oct 07 11:47:28 +0000 2018", "snapshot_id" : 40, "retweet_count" : "4", "id_tweet" : "1048883130600382464", "publisher_screen_name" : "Estadao", "bot_screen_name" : "tiagosi65456343", "impression_order" : 28, "tweet_created_at" : "3:30 AM - 7 Oct 2018", "publisher_id" : "9317502", "tweet_amount_of_likes" : "4", "tweet_amount_of_comments" : "4" }
{ "_id" : { "$oid" : "5bb9f273f5e0a646939a4079" }, "tweet_text" : "La Comunidad de Madrid de Cifuentes y Garrido: 64 asesores puestos a dedo con un sueldo medio de 55.663 euros al año y un perfil relacionado con el PP http:// ow.ly/dU2h30m8b6a &nbsp;", "snapshot_timestamp" : "Sun Oct 07 11:47:28 +0000 2018", "snapshot_id" : 40, "retweet_count" : "8", "id_tweet" : "1048881396654264321", "publisher_screen_name" : "el_pais", "bot_screen_name" : "tiagosi65456343", "impression_order" : 29, "tweet_created_at" : "3:23 AM - 7 Oct 2018", "publisher_id" : "7996082", "tweet_amount_of_likes" : "8", "tweet_amount_of_comments" : "8" }
{ "_id" : { "$oid" : "5bbf6825f5e0a65f4157c096" }, "snapshot_id" : 41, "retweet_count" : "1.2K", "impression_order" : 24, "tweet_created_at" : "6:44 PM - 7 Oct 2018", "snapshot_timestamp" : "Thu Oct 11 15:10:58 +0000 2018", "bot_screen_name" : "tiagosi65456343", "publisher_id" : "105155795", "tweet_amount_of_likes" : "1.2K", "tweet_text" : "Como democrata, eu respeito o resultado das urnas e cumprimento os dois candidatos que foram ao 2º turno. Fizemos uma campanha linda, baseada em propostas e propósitos. Infelizmente, caímos mais uma vez na velha polarização que se tornou tóxica", "publisher_screen_name" : "MarinaSilva", "tweet_amount_of_comments" : "1.2K", "id_tweet" : "1049113299659448325" }
{ "_id" : { "$oid" : "5bbf7657f5e0a65f4157c0b4" }, "snapshot_id" : 42, "retweet_count" : "1.2K", "impression_order" : 24, "tweet_created_at" : "6:44 PM - 7 Oct 2018", "snapshot_timestamp" : "Thu Oct 11 16:11:34 +0000 2018", "bot_screen_name" : "tiagosi65456343", "publisher_id" : "105155795", "tweet_amount_of_likes" : "1.2K", "tweet_text" : "Como democrata, eu respeito o resultado das urnas e cumprimento os dois candidatos que foram ao 2º turno. Fizemos uma campanha linda, baseada em propostas e propósitos. Infelizmente, caímos mais uma vez na velha polarização que se tornou tóxica", "publisher_screen_name" : "MarinaSilva", "tweet_amount_of_comments" : "1.2K", "id_tweet" : "1049113299659448325" }
